ErisPulse_EditVideoPlayer/Core.py
ErisPulse_EditVideoPlayer/__init__.py
ErisPulse_EditVideoPlayer/video_converter.py
erispulse_editvideoplayer-1.0.1.dist-info/licenses/LICENSE
erispulse_editvideoplayer-1.0.1.dist-info/METADATA
erispulse_editvideoplayer-1.0.1.dist-info/WHEEL
erispulse_editvideoplayer-1.0.1.dist-info/entry_points.txt
erispulse_editvideoplayer-1.0.1.dist-info/top_level.txt
erispulse_editvideoplayer-1.0.1.dist-info/RECORD
