Metadata-Version: 2.4
Name: ErisPulse-EditVideoPlayer
Version: 1.0.1
Summary: 一个通用的视频播放器模块，可将视频转换为点阵字符并在支持消息编辑的平台上播放
Author-email: wsu2059q <wsu2059@qq.com>
License: MIT License
Project-URL: homepage, https://github.com/wsu2059q/ErisPulse-EditVideoPlayer
Requires-Python: >=3.9
License-File: LICENSE
Requires-Dist: opencv-python-headless>=4.5.0
Requires-Dist: aiofiles>=0.8.0
Dynamic: license-file
